img_generation/__init__.py
img_generation/logger.py
img_generation/server.py
img_generation-0.1.1.dist-info/METADATA
img_generation-0.1.1.dist-info/WHEEL
img_generation-0.1.1.dist-info/entry_points.txt
img_generation-0.1.1.dist-info/licenses/LICENSE
img_generation-0.1.1.dist-info/RECORD
