Metadata-Version: 2.4
Name: img-generation
Version: 0.1.1
Summary: A MCP based image generation service project that provides the ability to convert HTML code images into images.
License-File: LICENSE
Requires-Python: >=3.12
Requires-Dist: boto3>=1.38.15
Requires-Dist: mcp>=1.7.1
Requires-Dist: playwright>=1.52.0
